[{"name": "Fundraising"}, {"name": "Social Entrepreneurship"}, {"name": "Business Strategy"}, {"name": "Research"}, {"name": "Nonprofits"}, {"name": "International Development"}, {"name": "Public Relations"}, {"name": "Analysis"}, {"name": "Entrepreneurship"}, {"name": "International Relations"}, {"name": "Politics"}, {"name": "Event Planning"}, {"name": "Editing"}, {"name": "Start-ups"}, {"name": "Political Science"}, {"name": "Microsoft Office"}, {"name": "PowerPoint"}, {"name": "Stata"}, {"name": "Qualitative Research"}, {"name": "Public Speaking"}, {"name": "Grants"}, {"name": "Agile Methodologies"}]