[{"name": "Editing"}, {"name": "M\u00e9dia num\u00e9rique", "standardizedSkillUrn": "urn:li:fs_miniSkill:1599", "standardizedSkill": {"name": "Digital Media", "entityUrn": "urn:li:fs_miniSkill:1599"}}, {"name": "Correction de texte", "standardizedSkillUrn": "urn:li:fs_miniSkill:1448", "standardizedSkill": {"name": "Proofreading", "entityUrn": "urn:li:fs_miniSkill:1448"}}, {"name": "Fran\u00e7ais", "standardizedSkillUrn": "urn:li:fs_miniSkill:605", "standardizedSkill": {"name": "French", "entityUrn": "urn:li:fs_miniSkill:605"}}, {"name": "Anglais", "standardizedSkillUrn": "urn:li:fs_miniSkill:274", "standardizedSkill": {"name": "English", "entityUrn": "urn:li:fs_miniSkill:274"}}]