[{"name": "Strat\u00e9gie d\u2019entreprise", "standardizedSkillUrn": "urn:li:fs_miniSkill:697", "standardizedSkill": {"name": "Business Strategy", "entityUrn": "urn:li:fs_miniSkill:697"}}, {"name": "Secteur public", "standardizedSkillUrn": "urn:li:fs_miniSkill:880", "standardizedSkill": {"name": "Public Sector", "entityUrn": "urn:li:fs_miniSkill:880"}}, {"name": "D\u00e9veloppement commercial"}, {"name": "Entrepreneuriat", "standardizedSkillUrn": "urn:li:fs_miniSkill:1735", "standardizedSkill": {"name": "Entrepreneurship", "entityUrn": "urn:li:fs_miniSkill:1735"}}, {"name": "Business-to-Business (BtoB)", "standardizedSkillUrn": "urn:li:fs_miniSkill:853", "standardizedSkill": {"name": "Business-to-Business (B2B)", "entityUrn": "urn:li:fs_miniSkill:853"}}, {"name": "Vente de solutions", "standardizedSkillUrn": "urn:li:fs_miniSkill:1750", "standardizedSkill": {"name": "Solution Selling", "entityUrn": "urn:li:fs_miniSkill:1750"}}, {"name": "Financement structur\u00e9", "standardizedSkillUrn": "urn:li:fs_miniSkill:1820", "standardizedSkill": {"name": "Structured Finance", "entityUrn": "urn:li:fs_miniSkill:1820"}}, {"name": "Gestion de projet"}, {"name": "Conseil"}, {"name": "Gestion de la relation client (CRM)"}, {"name": "strat\u00e9gie commerciale"}, {"name": "Gestion des ventes"}, {"name": "Logiciel en tant que Service (SaaS)", "standardizedSkillUrn": "urn:li:fs_miniSkill:2326", "standardizedSkill": {"name": "Software as a Service (SaaS)", "entityUrn": "urn:li:fs_miniSkill:2326"}}, {"name": "Management"}, {"name": "n\u00e9gociation de contrat"}, {"name": "Leadership"}, {"name": "Services de conseil", "standardizedSkillUrn": "urn:li:fs_miniSkill:2640", "standardizedSkill": {"name": "Consultancy Services", "entityUrn": "urn:li:fs_miniSkill:2640"}}, {"name": "D\u00e9veloppement de start-up", "standardizedSkillUrn": "urn:li:fs_miniSkill:30499", "standardizedSkill": {"name": "Startup Development", "entityUrn": "urn:li:fs_miniSkill:30499"}}, {"name": "RGPD"}, {"name": "Droit des soci\u00e9t\u00e9s"}, {"name": "Droit des affaires"}]